{
  "vix": {
    "value": 17.16,
    "prev": 15.03,
    "change_pct": 14.17
  },
  "sp500": {
    "value": 7515.34,
    "prev": 7575.39,
    "change_pct": -0.79
  },
  "sox": {
    "value": 12347.78,
    "prev": 12967.16,
    "change_pct": -4.78
  },
  "us3m": {
    "value": 3.73,
    "prev": 3.69,
    "change_pct": 0.89
  },
  "us10y": {
    "value": 4.61,
    "prev": 4.57,
    "change_pct": 0.88
  },
  "hyg": {
    "value": 79.52,
    "prev": 79.71,
    "change_pct": -0.24
  },
  "gold": {
    "value": 4021.5,
    "prev": 4104.1,
    "change_pct": -2.01
  },
  "oil": {
    "value": 78.99,
    "prev": 71.41,
    "change_pct": 10.61
  },
  "copper": {
    "value": 6.31,
    "prev": 6.23,
    "change_pct": 1.3
  },
  "jpy": {
    "value": 162.35,
    "prev": 161.88,
    "change_pct": 0.29
  },
  "dxy": {
    "value": 101.2,
    "prev": 100.97,
    "change_pct": 0.22
  },
  "twii": {
    "value": 44086.66,
    "prev": 45380.52,
    "change_pct": -2.85
  },
  "tsmc": {
    "value": 2410.0,
    "prev": 2440.0,
    "change_pct": -1.23
  },
  "usdtwd": {
    "value": 32.1,
    "prev": 32.1,
    "change_pct": 0.01
  },
  "sse": {
    "value": 3908.26,
    "prev": 3913.79,
    "change_pct": -0.14
  },
  "sp500_ma200": 6969.43,
  "twii_ma20": 45976.13,
  "tsmc_ma60": 2308.06,
  "fear_greed": {
    "value": null,
    "rating": "N/A"
  },
  "twse_foreign": {
    "value": -180.8
  },
  "twse_margin": {
    "value": null,
    "change_pct": null
  },
  "twse_volume": {
    "value": 10676.6
  },
  "updated_utc": "2026-07-14 02:44 UTC",
  "updated_tw": "2026-07-14 10:44 台灣時間"
}